{
	"name": "Escena 3",
	"layers": [
		{
			"name": "Capa 0",
			"overriden": 0,
			"subLayers": [],
			"instances": [
				{
					"type": "partesinternasordenador",
					"properties": {
						"initially-visible": true,
						"initial-animation": "Default",
						"initial-frame": 0,
						"enable-collisions": true,
						"live-preview": false
					},
					"uid": 27,
					"sid": 777584610171464,
					"tags": "",
					"instanceVariables": {},
					"behaviors": {},
					"instanceFolderItem": {
						"sid": 777584610171464,
						"expanded": true,
						"folderName": "",
						"indexInFolder": -1,
						"folderNestingLevel": -1
					},
					"showing": true,
					"locked": false,
					"world": {
						"x": 424,
						"y": 239,
						"width": 610.6148617377405,
						"height": 407.7136270340677,
						"originX": 0.5,
						"originY": 0.5,
						"color": [
							1,
							1,
							1,
							1
						],
						"angle": 0,
						"zElevation": 0
					}
				},
				{
					"type": "flecha2",
					"properties": {
						"initially-visible": true,
						"initial-animation": "Default",
						"initial-frame": 0,
						"enable-collisions": true,
						"live-preview": false
					},
					"uid": 28,
					"sid": 122251100705715,
					"tags": "",
					"instanceVariables": {},
					"behaviors": {},
					"instanceFolderItem": {
						"sid": 122251100705715,
						"expanded": true,
						"folderName": "",
						"indexInFolder": -1,
						"folderNestingLevel": -1
					},
					"showing": true,
					"locked": false,
					"world": {
						"x": 50,
						"y": 442,
						"width": 59.82855413534533,
						"height": 61.82855413534533,
						"originX": 0.5,
						"originY": 0.5,
						"color": [
							1,
							1,
							1,
							1
						],
						"angle": 3.141592653589793,
						"zElevation": 0
					}
				}
			],
			"sid": 870035717830554,
			"effectTypes": [],
			"isInitiallyVisible": true,
			"isInitiallyInteractive": true,
			"isHTMLElementsLayer": false,
			"color": [
				1,
				1,
				1,
				1
			],
			"backgroundColor": [
				0.3686274509803922,
				0.3686274509803922,
				0.3686274509803922,
				1
			],
			"isTransparent": false,
			"parallaxX": 1,
			"parallaxY": 1,
			"scaleRate": 1,
			"forceOwnTexture": false,
			"renderingMode": "3d",
			"drawOrder": "z-order",
			"useRenderCells": false,
			"blendMode": "normal",
			"zElevation": 0,
			"global": false
		}
	],
	"scene-graphs-folder-root": {
		"items": [],
		"subfolders": []
	},
	"sid": 333776263339895,
	"nonworld-instances": [],
	"effectTypes": [],
	"width": 1708,
	"height": 960,
	"unboundedScrolling": false,
	"vpX": 0.5,
	"vpY": 0.5,
	"projection": "perspective",
	"eventSheet": null
}